iotile/__init__.py
iotile/core/__init__.py
iotile/core/config_variables.py
iotile/core/exceptions.py
iotile/core/dev/__init__.py
iotile/core/dev/annotated_registry.py
iotile/core/dev/config.py
iotile/core/dev/iotileobj.py
iotile/core/dev/registry.py
iotile/core/dev/semver.py
iotile/core/hw/__init__.py
iotile/core/hw/exceptions.py
iotile/core/hw/hwmanager.py
iotile/core/hw/app/__init__.py
iotile/core/hw/app/app.py
iotile/core/hw/app/info_app.py
iotile/core/hw/app/updater_app.py
iotile/core/hw/auth/__init__.py
iotile/core/hw/auth/auth_chain.py
iotile/core/hw/auth/auth_provider.py
iotile/core/hw/auth/cli_auth_provider.py
iotile/core/hw/auth/default_providers.py
iotile/core/hw/auth/env_auth_provider.py
iotile/core/hw/auth/inmemory_auth_provider.py
iotile/core/hw/auth/null_auth_provider.py
iotile/core/hw/auth/rootkey_auth_provider.py
iotile/core/hw/debug/__init__.py
iotile/core/hw/debug/debug_manager.py
iotile/core/hw/debug/flash_board_step.py
iotile/core/hw/debug/sparse_memory.py
iotile/core/hw/proxy/__init__.py
iotile/core/hw/proxy/external_proxy.py
iotile/core/hw/proxy/plugin.py
iotile/core/hw/proxy/proxy.py
iotile/core/hw/reports/__init__.py
iotile/core/hw/reports/broadcast.py
iotile/core/hw/reports/flexible_dictionary.py
iotile/core/hw/reports/individual_format.py
iotile/core/hw/reports/parser.py
iotile/core/hw/reports/report.py
iotile/core/hw/reports/signed_list_format.py
iotile/core/hw/reports/utc_assigner.py
iotile/core/hw/transport/__init__.py
iotile/core/hw/transport/adapterstream.py
iotile/core/hw/transport/virtualadapter.py
iotile/core/hw/transport/adapter/__init__.py
iotile/core/hw/transport/adapter/abstract.py
iotile/core/hw/transport/adapter/async_wrapper.py
iotile/core/hw/transport/adapter/legacy.py
iotile/core/hw/transport/adapter/mixin_conndata.py
iotile/core/hw/transport/adapter/mixin_notifications.py
iotile/core/hw/transport/adapter/standard.py
iotile/core/hw/transport/adapter/sync_wrapper.py
iotile/core/hw/transport/server/__init__.py
iotile_core-5.2.0.dist-info/LICENSE.md
iotile_core-5.2.0.dist-info/METADATA
iotile_core-5.2.0.dist-info/WHEEL
iotile_core-5.2.0.dist-info/entry_points.txt
iotile_core-5.2.0.dist-info/top_level.txt
iotile_core-5.2.0.dist-info/RECORD
