Metadata-Version: 2.1
Name: iotile-core
Version: 5.2.0
Summary: IOTile Core Tools
Home-page: https://github.com/iotile/coretools/iotilecore
Author: Arch
Author-email: info@arch-iot.com
License: LGPLv3
Keywords: iotile,arch,embedded,hardware
Platform: UNKNOWN
Classifier: Programming Language :: Python
Classifier: Development Status :: 5 - Production/Stable
Classifier: License :: OSI Approved :: GNU Library or Lesser General Public License (LGPL)
Classifier: Operating System :: OS Independent
Classifier: Programming Language :: Python :: 3
Classifier: Programming Language :: Python :: 3.7
Classifier: Programming Language :: Python :: 3.8
Classifier: Programming Language :: Python :: 3.9
Classifier: Topic :: Software Development :: Libraries :: Python Modules
Requires-Python: >=3.7, <4
Requires-Dist: crcmod (<2,>=1.7)
Requires-Dist: entrypoints (<1,>=0.3.0)
Requires-Dist: intelhex (>=2.3)
Requires-Dist: msgpack (>=1)
Requires-Dist: python-dateutil (>=2.8)
Requires-Dist: typedargs (>=1.1.2)
Provides-Extra: ui
Requires-Dist: asciimatics (<2,>=1.10.0) ; extra == 'ui'
